builddeck/__init__.py
builddeck/cli.py
builddeck/helpers/__init__.py
builddeck/helpers/config.py
builddeck/helpers/docker_compose.py
builddeck/helpers/docker_manager.py
builddeck/helpers/get_logging.py
builddeck/helpers/processes.py
builddeck/helpers/test_services.py
builddeck/helpers/versioning.py
BuildDeck-2.0.8.dist-info/LICENSE
BuildDeck-2.0.8.dist-info/METADATA
BuildDeck-2.0.8.dist-info/WHEEL
BuildDeck-2.0.8.dist-info/entry_points.txt
BuildDeck-2.0.8.dist-info/top_level.txt
BuildDeck-2.0.8.dist-info/RECORD
