Metadata-Version: 2.1
Name: BuildDeck
Version: 2.0.8
Summary: A CLI tool for managing services and deployments.
Home-page: https://github.com/rmhy-tech/builddeck
Author: Leul Tewolde
Author-email: leul@mereb.app
License: UNKNOWN
Platform: UNKNOWN
Classifier: Programming Language :: Python :: 3
Classifier: License :: OSI Approved :: MIT License
Classifier: Operating System :: OS Independent
Requires-Python: >=3.7
License-File: LICENSE
Requires-Dist: Click~=8.1.3
Requires-Dist: PyYAML~=6.0.2
Requires-Dist: requests~=2.32.3
Requires-Dist: colorlog~=6.8.2
Requires-Dist: docker~=7.1.0
